{
    "$schema": "http://schema.management.azure.com/schemas/2015-01-01/deploymentTemplate.json#",
    "contentVersion": "1.0.0.0",
    "parameters": {
        "dataFactoryName": {
            "type": "string"
        },
        "baseUrl": {
            "type": "string"
        },
        "Storagekey": {
            "type": "securestring"
        },
        "servicePrincipalId": {
            "type": "string"
        },
        "hostSubscriptionId": {
            "type": "string"
        },
        "tenant": {
            "type": "string"
        },
        "ClusterUserName": {
            "type": "string"
        },
        "ClusterPassword": {
            "type": "securestring"
        },
        "sqlseverkey": {
            "type": "securestring"
        },
        "environment": {
            "type": "string",
            "allowedValues": [
                "Development",
                "Production"
            ]
        },
        "resourcesgpname": {
            "type": "string"
        }
    },
    "variables": {
        "dataFactoryName": "[parameters('dataFactoryName')]",
        "baseUrl": "[parameters('baseUrl')]",
        "accesskey": "[parameters('Storagekey')]",
        "spkey": "[parameters('spkey')]",
        "servicePrincipalId": "[parameters('servicePrincipalId')]",
        "hostSubscriptionId": "[parameters('hostSubscriptionId')]",
        "tenant": "[parameters('tenant')]",
        "ClusterUserName": "[parameters('ClusterUserName')]",
        "ClusterPassword": "[parameters('ClusterPassword')]",
        "sqlseverkey": "[parameters('sqlseverkey')]",
        "Development": 2,
        "Production": 4,
        "Instancesize": "[if(equals(parameters('environment'), 'Development'), variables('Development'), variables('Production'))]",
        "resourcesgpname": "[parameters('resourcesgpname')]"

    },
    "resources": [
        {
            "name": "adf",
            "type": "Microsoft.Resources/deployments",
            "apiVersion": "2017-05-10",
            "properties": {
                "templateLink": {
                    "uri": "https://raw.githubusercontent.com/sangaml/testing_repo/master/BigData/createadf.json",
                    "contentVersion": "1.0.0.0"
                },
                "parameters": {
                    "dataFactoryName": {
                        "value": "[variables('dataFactoryName')]"
                    }
                },
                "mode": "Incremental"
            }
        },
        {
            "name": "keyvault_ls",
            "type": "Microsoft.Resources/deployments",
            "apiVersion": "2017-05-10",
            "properties": {
                "templateLink": {
                    "uri": "https://raw.githubusercontent.com/sangaml/testing_repo/master/BigData/key_vault_ls.json",
                    "contentVersion": "1.0.0.0"
                },
                "parameters": {
                    "baseUrl": {
                        "value": "[variables('baseUrl')]"
                    }
                },
                "mode": "Incremental"
            },
            "dependsOn": [
                "[concat('Microsoft.Resources/deployments/', 'adf')]"
            ] 
        },
        {
            "name": "lsazureblob",
            "type": "Microsoft.Resources/deployments",
            "apiVersion": "2017-05-10",
            "properties": {
                "templateLink": {
                    "uri": "https://raw.githubusercontent.com/sangaml/testing_repo/master/BigData/blob_storage_keyvault_ls.json",
                    "contentVersion": "1.0.0.0"
                },
                "parameters": {
                    "accesskey": {
                        "value": "[variables('accesskey')]"
                    },
                    "dataFactoryName": {
                        "value": "[variables('dataFactoryName')]"
                    }
                },
                "mode": "Incremental"
            },
            "dependsOn": [
                "[concat('Microsoft.Resources/deployments/', 'adf')]",
                "[concat('Microsoft.Resources/deployments/', 'keyvault_ls')]"
            ]
        },
        {
            "name": "lsondemandhdinsight",
            "type": "Microsoft.Resources/deployments",
            "apiVersion": "2017-05-10",
            "properties": {
                "templateLink": {
                    "uri": "https://raw.githubusercontent.com/sangaml/testing_repo/master/BigData/ondemand_hive_keyvault.json",
                    "contentVersion": "1.0.0.0"
                },
                "parameters": {
                    "spkey": {
                        "value": "[variables('spkey')]"
                    },
                    "servicePrincipalId": {
                        "value": "[variables('servicePrincipalId')]"
                    },
                    "hostSubscriptionId": {
                        "value": "[variables('hostSubscriptionId')]"
                    },
                    "tenant": {
                        "value": "[variables('tenant')]"
                    },
                    "dataFactoryName": {
                        "value": "[variables('dataFactoryName')]"
                    },
                    "ClusterUserName": {
                        "value": "[variables('ClusterUserName')]"
                    },
                    "ClusterPassword": {
                        "value": "[variables('ClusterPassword')]"
                    },
                    "Instancesize": {
                        "value": "[variables('Instancesize')]"
                    },
                    "resourcesgpname": {
                        "value": "[variables('resourcesgpname')]"
                    }
                },
                "mode": "Incremental"
            },
            "dependsOn": [
                "[concat('Microsoft.Resources/deployments/', 'lsazureblob')]",
                "[concat('Microsoft.Resources/deployments/', 'adf')]",
                "[concat('Microsoft.Resources/deployments/', 'keyvault_ls')]"
            ]
        },
        {
            "name": "hivepipeline",
            "type": "Microsoft.Resources/deployments",
            "apiVersion": "2017-05-10",
            "properties": {
                "templateLink": {
                    "uri": "https://raw.githubusercontent.com/sangaml/testing_repo/master/BigData/adf_pipeline_hive.json",
                    "contentVersion": "1.0.0.0"
                },
                "parameters": {
                    "dataFactoryName": {
                        "value": "[variables('dataFactoryName')]"
                    }
                },
                "mode": "Incremental"
            },
            "dependsOn": [
                "[concat('Microsoft.Resources/deployments/', 'lsazureblob')]",
                "[concat('Microsoft.Resources/deployments/', 'lsondemandhdinsight')]",
                "[concat('Microsoft.Resources/deployments/', 'adf')]",
                "[concat('Microsoft.Resources/deployments/', 'keyvault_ls')]"
            ]
        },
        {
            "name": "lssqlserver",
            "type": "Microsoft.Resources/deployments",
            "apiVersion": "2017-05-10",
            "properties": {
                "templateLink": {
                    "uri": "https://raw.githubusercontent.com/sangaml/testing_repo/master/BigData/sqlserver_keyvault_ls.json",
                    "contentVersion": "1.0.0.0"
                },
                "parameters": {
                    "dataFactoryName": {
                        "value": "[variables('dataFactoryName')]"
                    },
                    "sqlseverkey": {
                        "value": "[variables('sqlseverkey')]"
                    }
                },
                "mode": "Incremental"
            },
            "dependsOn": [
                "[concat('Microsoft.Resources/deployments/', 'lsazureblob')]",
                "[concat('Microsoft.Resources/deployments/', 'lsondemandhdinsight')]",
                "[concat('Microsoft.Resources/deployments/', 'adf')]",
                "[concat('Microsoft.Resources/deployments/', 'hivepipeline')]",
                "[concat('Microsoft.Resources/deployments/', 'keyvault_ls')]"
            ] 
        },
        {
            "name": "copypipeline",
            "type": "Microsoft.Resources/deployments",
            "apiVersion": "2017-05-10",
            "properties": {
                "templateLink": {
                    "uri": "https://raw.githubusercontent.com/sangaml/testing_repo/master/BigData/adf_pipeline_copy.json",
                    "contentVersion": "1.0.0.0"
                },
                "parameters": {
                    "dataFactoryName": {
                        "value": "[variables('dataFactoryName')]"
                    }
                },
                "mode": "Incremental"
            },
            "dependsOn": [
                "[concat('Microsoft.Resources/deployments/', 'lsazureblob')]",
                "[concat('Microsoft.Resources/deployments/', 'lsondemandhdinsight')]",
                "[concat('Microsoft.Resources/deployments/', 'adf')]",
                "[concat('Microsoft.Resources/deployments/', 'hivepipeline')]",
                "[concat('Microsoft.Resources/deployments/', 'lssqlserver')]",
                "[concat('Microsoft.Resources/deployments/', 'keyvault_ls')]"
            ] 
        },
        {
            "name": "copy_trigger",
            "type": "Microsoft.Resources/deployments",
            "apiVersion": "2017-05-10",
            "properties": {
                "templateLink": {
                    "uri": "https://raw.githubusercontent.com/sangaml/testing_repo/master/BigData/scheduletrigger.json",
                    "contentVersion": "1.0.0.0"
                },
                "parameters": {
                    "dataFactoryName": {
                        "value": "[variables('dataFactoryName')]"
                    }
                },
                "mode": "Incremental"
            },
            "dependsOn": [
                "[concat('Microsoft.Resources/deployments/', 'lsazureblob')]",
                "[concat('Microsoft.Resources/deployments/', 'lsondemandhdinsight')]",
                "[concat('Microsoft.Resources/deployments/', 'adf')]",
                "[concat('Microsoft.Resources/deployments/', 'hivepipeline')]",
                "[concat('Microsoft.Resources/deployments/', 'lssqlserver')]",
                "[concat('Microsoft.Resources/deployments/', 'copypipeline')]",
                "[concat('Microsoft.Resources/deployments/', 'keyvault_ls')]"
            ] 
        }
    ]
}
